{
    "modules" : {

        "base": {
            "forportal": true,
            "forclients": true,
            "api" : [ "datatypes", "dynamic", "dynamicattributes", "clientsettings", "login", "menu", "permissions", "relations", "search", "settingsets", "translations", "usergroups", "users" ],
            "middlewares": [ "auth", "extracttoken", "nocache", "validateSameClientId" ],
            "public" : [
                "css/angular-material.min.css",
                "css/base.css",
                "css/logo_avorium_komplett.svg",
                "css/icons/material/Add Link.svg",
                "css/icons/material/Briefcase.svg",
                "css/icons/material/Cancel.svg",
                "css/icons/material/Checked Checkbox.svg",
                "css/icons/material/Delete.svg",
                "css/icons/material/Edit.svg",
                "css/icons/material/Exit.svg",
                "css/icons/material/Forward.svg",
                "css/icons/material/Help.svg",
                "css/icons/material/List.svg",
                "css/icons/material/Menu.svg",
                "css/icons/material/Menu2.svg",
                "css/icons/material/Menu black.svg",
                "css/icons/material/Plus Math.svg",
                "css/icons/material/Text Box.svg",
                "css/icons/material/User.svg",
                "css/icons/material/User Group Man Man.svg",
                "css/icons/material/Search.svg",
                "css/icons/material/Settings.svg",
                "css/icons/material/View Details.svg",
                "css/icons/office/Add Link.svg",
                "css/icons/office/Briefcase.svg",
                "css/icons/office/Cancel.svg",
                "css/icons/office/Delete.svg",
                "css/icons/office/Edit.svg",
                "css/icons/office/Exit.svg",
                "css/icons/office/Menu.svg",
                "css/icons/office/Plus Math.svg",
                "css/icons/office/User.svg",
                "css/icons/office/User Group Man Man.svg",
                "css/icons/office/Search.svg",
                "css/icons/office/Settings.svg",
                "css/icons/office/View Details.svg",
                "css/images/Settings_clients.png",
                "css/images/Settings_dynamicattributes.png",
                "css/images/Settings_dynamicattributes_addattribute.png",
                "css/images/Settings_dynamicattributes_addlistelement.png",
                "css/images/Settings_dynamicattributes_editlistelement.png",
                "css/images/Settings_dynamicattributes_entity.png",
                "css/images/Settings_dynamicattributes_entitylist.png",
                "css/images/Settings_dynamicattributes_listelements.png",
                "css/images/Settings_dynamicattributes_newattribute.png",
                "css/images/Settings_portals.png",
                "css/images/Settings_portals_auto_update.png",
                "css/images/Settings_portals_update.png",
                "css/images/Settings_users.png",
                "css/images/Users_add_button.png",
                "css/images/Users_edituser.png",
                "css/images/Users_list.png",
                "css/images/Usergroups_add.png",
                "css/images/Usergroups_editdetails.png",
                "css/images/Usergroups_list.png",
                "css/images/Usergroups_permissions.png",
                "partial/Administration/ClientSettingsCard.html",
                "partial/Administration/DynamicAttributeCreationFormCard.html",
                "partial/Administration/DynamicAttributesCard.html",
                "partial/Administration/DynamicAttributeElementCard.html",
                "partial/Administration/DynamicAttributesEntityListCard.html",
                "partial/Administration/SettingSetListCard.html",
                "partial/Administration/UserCard.html",
                "partial/Administration/UsergroupCard.html",
                "partial/Administration/UsergrouplistCard.html",
                "partial/Administration/UserlistCard.html",
                "partial/Administration/UserSettingsCard.html",
                "partial/components/DetailsCard.html",
                "partial/components/HierarchyCard.html",
                "partial/Core/DynamicAttributesTab.html",
                "partial/Doc/Settings.html",
                "partial/Doc/Users.html",
                "partial/Doc/UserGroups.html",
                "_index.html",
                "chat.html",
                "favicon.png"
            ],
            "root" : [ "app.js", "package.json", "package-lock.json", "installwindowsservice.js", "uninstallwindowsservice.js", "keeprunning.js", "triggerupdate.js", "config/localconfig.json.template" ],
            "include" : [
                "public/js/lib/angular.min.js",
                "public/js/lib/angular-aria.min.js",
                "public/js/lib/angular-animate.min.js",
                "public/js/lib/angular-material.min.js",
                "public/js/lib/angular-messages.min.js",
                "public/js/lib/moment.min.js",
                "public/js/lib/angular-moment.min.js",
                "public/js/lib/angular-route.min.js",
                "public/js/lib/angular-sanitize.min.js",
                "public/js/lib/angular-translate.min.js",
                "public/js/lib/angular-translate-loader-static-files.min.js",
                "public/js/lib/locale/de.js",
                "public/js/AppSetup.js",
                "public/js/Utils.js",
                "public/js/MainController.js",

                "public/js/components/avt-card.js",
                "public/js/components/avt-details.js",
                "public/js/components/avt-hierarchy.js",
                "public/js/components/avt-relations-tab.js",
                "public/js/components/avt-relations-toolbar-button.js",
                "public/js/components/avt-toolbar.js",
                "public/js/components/avt-toolbar-button.js",

                "public/js/Administration/ClientSettingsCardController.js",
                "public/js/Administration/DynamicAttributesCardController.js",
                "public/js/Administration/DynamicAttributeCreationFormCardController.js",
                "public/js/Administration/DynamicAttributeElementCardController.js",
                "public/js/Administration/DynamicAttributesEntityListCardController.js",
                "public/js/Administration/SettingSetListCardController.js",
                "public/js/Administration/UserCardController.js",
                "public/js/Administration/UsergroupCardController.js",
                "public/js/Administration/UsergrouplistCardController.js",
                "public/js/Administration/UserlistCardController.js",
                "public/js/Administration/UserSettingsCardController.js"
            ],
            "languages" : [ "en", "de" ],
            "menu": [
                {
                    "title": "TRK_MENU_ADMINISTRATION",
                    "items": [
                        { "mainCard": "Administration/SettingSetListCard", "icon": "/css/icons/material/Settings.svg", "title": "TRK_MENU_ADMINISTRATION_SETTINGS", "permission": "PERMISSION_ADMINISTRATION_SETTINGS", "docCard" : "Settings" },
                        { "mainCard": "Administration/UserlistCard", "icon": "/css/icons/material/User.svg", "title": "TRK_MENU_ADMINISTRATION_USERS", "permission" : "PERMISSION_ADMINISTRATION_USER", "docCard" : "Users", "directurls": [ "users" ] },
                        { "mainCard": "Administration/UsergrouplistCard", "icon": "/css/icons/material/User Group Man Man.svg", "title": "TRK_MENU_ADMINISTRATION_USERGROUPS", "permission" : "PERMISSION_ADMINISTRATION_USERGROUP", "docCard" : "UserGroups", "directurls": [ "usergroups" ] }
                    ]
                }
            ],
            "utils": [ "apiHelper", "calculationhelper", "configHelper", "constants", "dynamicAttributesHelper", "relationsHelper", "db", "localConfigHelper", "permissionshelper", "updateonstart" ],
            "permissions" : [ "PERMISSION_CORE_RELATIONS" ],
            "settingsets" : [
                { "mainCard": "Administration/UserSettingsCard", "title": "TRK_SETTINGSET_USER_GENERAL", "type": "SETTINGSET_TYPE_USER", "icon": "User", "permission": "PERMISSION_SETTINGS_USER"},
                { "mainCard": "Administration/ClientSettingsCard", "title": "TRK_SETTINGSET_CLIENT", "type": "SETTINGSET_TYPE_CLIENT", "icon": "Briefcase", "permission": "PERMISSION_SETTINGS_CLIENT"},
                { "mainCard": "Administration/DynamicAttributesEntityListCard", "title": "TRK_SETTINGSET_DYNAMICATTRIBUTES", "type": "SETTINGSET_TYPE_CLIENT", "icon": "View Details", "permission": "PERMISSION_SETTINGS_CLIENT_DYNAMICATTRIBUTES"}
            ],
            "clientdatatypes": [

                { "name": "dynamicattributetypes", "label": "Attributart", "titlefield": "label", "fields": [
                    { "name": "label", "type": "text" }
                ], "values": [
                    { "name": "text", "label": "Textfeld" },
                    { "name": "boolean", "label": "Boolescher Wert" },
                    { "name": "picklist", "label": "Auswahlliste" }
                ] }, 

                { "name": "dynamicattributes", "label": "Dynamisches Attribut", "plurallabel": "Dynamische Attribute", "titlefield": "label", "fields": [
                    { "name": "modelname", "type": "text" },
                    { "name": "label", "label": "Bezeichnung", "type": "text" },
                    { "name": "isinactive", "label": "Inaktiv", "type": "boolean" },
                    { "name": "dynamicattributetypename", "label": "Typ", "type": "reference", "reference": "dynamicattributetypes" },
                    { "name": "identifier", "type": "text" }
                ] },

                { "name": "dynamicattributeoptions", "label": "Listenelement", "plurallabel": "Listenelemente", "titlefield": "label", "fields": [
                    { "name": "dynamicattributename", "type": "reference", "reference": "dynamicattributes" },
                    { "name": "label", "label": "Bezeichnung", "type": "text" },
                    { "name": "value", "label": "Wert", "type": "text" }
                ] },

                { "name": "dynamicattributevalues", "fields": [
                    { "name": "entityname", "type": "text" },
                    { "name": "dynamicattributename", "type": "reference", "reference": "dynamicattributes" },
                    { "name": "value", "type": "text" }
                ] }, 

                { "name": "relations", "label": "Verknüpfung", "plurallabel": "Verknüpfungen", "fields": [
                    { "name": "datatype1name", "type": "text" },
                    { "name": "name1", "type": "text" },
                    { "name": "datatype2name", "type": "text" },
                    { "name": "name2", "type": "text" },
                    { "name": "relationtypename", "type": "reference", "reference": "relationtypes" }
                ] },

                { "name": "relationtypes", "label": "Verknüpfungsart", "plurallabel": "Verknüpfungsarten", "titlefield": "label", "fields": [
                    { "name": "label", "label": "Bezeichnung", "type": "text" },
                    { "name": "labelfrom1to2", "label": "Beziehung von A zu B", "type": "text" },
                    { "name": "labelfrom2to1", "label": "Beziehung von B zu A", "type": "text" }
                ], "values": [
                    { "name": "dependency", "label": "Abhängigkeit", "labelfrom1to2": "Ist abhängig von", "labelfrom2to1": "Bedingt" },
                    { "name": "looselycoupled", "label": "Lose Beziehung", "labelfrom1to2": "Steht in Zusammenhang mit", "labelfrom2to1": "Steht in Zusammenhang mit" },
                    { "name": "parentchild", "label": "Eltern-Kind-Beziehung", "labelfrom1to2": "Ist Elternteil von", "labelfrom2to1": "Ist Kind von" }
                ]},

                { "name": "usergroups", "label": "Benutzergruppe", "plurallabel": "Benutzergruppen", "titlefield": "name", "icon": "/css/icons/material/User Group Man Man.svg", "fields": [
                    { "name": "label", "label": "Bezeichnung", "type": "text" }
                ], "canhaverelations" : true },

                { "name": "users", "label": "Benutzer", "plurallabel": "Benutzer", "titlefield": "name", "icon": "/css/icons/material/User.svg", "fields": [
                    { "name": "label", "label": "Bezeichnung", "type": "text" },
                    { "name": "password", "label": "Passwort", "type": "text" },
                    { "name": "isadmin", "label": "Administrator", "type": "boolean" },
                    { "name": "usergroupname", "label": "Benutzergruppe", "type": "reference", "reference": "usergroups" }
                ], "canhaverelations" : true }

            ],
            "portaldatatypes": [

                { "name": "clientsettings", "label": "Mandanteneinstellung", "plurallabel": "Mandanteneinstellungen", "fields": [
                    { "name": "logourl", "label": "Logo URL", "type": "text" },
                    { "name": "clientname", "label": "Mandant", "type": "reference", "reference": "clients" }
                ] },

                { "name": "dynamicattributetypes", "label": "Attributart", "titlefield": "label", "fields": [
                    { "name": "label", "type": "text" }
                ], "values": [
                    { "name": "text", "label": "Textfeld" },
                    { "name": "boolean", "label": "Boolescher Wert" },
                    { "name": "picklist", "label": "Auswahlliste" }
                ] }, 

                { "name": "dynamicattributes", "label": "Dynamisches Attribut", "plurallabel": "Dynamische Attribute", "titlefield": "label", "fields": [
                    { "name": "modelname", "type": "text" },
                    { "name": "label", "label": "Bezeichnung", "type": "text" },
                    { "name": "isinactive", "label": "Inaktiv", "type": "boolean" },
                    { "name": "dynamicattributetypename", "label": "Typ", "type": "reference", "reference": "dynamicattributetypes" },
                    { "name": "identifier", "type": "text" }
                ] },

                { "name": "dynamicattributeoptions", "label": "Listenelement", "plurallabel": "Listenelemente", "titlefield": "label", "fields": [
                    { "name": "dynamicattributename", "type": "reference", "reference": "dynamicattributes" },
                    { "name": "label", "label": "Bezeichnung", "type": "text" },
                    { "name": "value", "label": "Wert", "type": "text" }
                ] },

                { "name": "dynamicattributevalues", "fields": [
                    { "name": "entityname", "type": "text" },
                    { "name": "dynamicattributename", "type": "reference", "reference": "dynamicattributes" },
                    { "name": "value", "type": "text" }
                ] }, 

                { "name": "relations", "label": "Verknüpfung", "plurallabel": "Verknüpfungen", "fields": [
                    { "name": "datatype1name", "type": "text" },
                    { "name": "name1", "type": "text" },
                    { "name": "datatype2name", "type": "text" },
                    { "name": "name2", "type": "text" },
                    { "name": "relationtypename", "type": "reference", "reference": "relationtypes" }
                ] },

                { "name": "relationtypes", "label": "Verknüpfungsart", "plurallabel": "Verknüpfungsarten", "titlefield": "label", "fields": [
                    { "name": "label", "label": "Bezeichnung", "type": "text" },
                    { "name": "labelfrom1to2", "label": "Beziehung von A zu B", "type": "text" },
                    { "name": "labelfrom2to1", "label": "Beziehung von B zu A", "type": "text" }
                ], "values": [
                    { "name": "dependency", "label": "Abhängigkeit", "labelfrom1to2": "Ist abhängig von", "labelfrom2to1": "Bedingt" },
                    { "name": "looselycoupled", "label": "Lose Beziehung", "labelfrom1to2": "Steht in Zusammenhang mit", "labelfrom2to1": "Steht in Zusammenhang mit" },
                    { "name": "parentchild", "label": "Eltern-Kind-Beziehung", "labelfrom1to2": "Ist Elternteil von", "labelfrom2to1": "Ist Kind von" }
                ]},

                { "name": "usergroups", "label": "Benutzergruppe", "plurallabel": "Benutzergruppen", "titlefield": "name", "icon": "/css/icons/material/User Group Man Man.svg", "fields": [
                    { "name": "label", "label": "Bezeichnung", "type": "text" }
                ], "canhaverelations" : true },

                { "name": "users", "label": "Benutzer", "plurallabel": "Benutzer", "titlefield": "name", "icon": "/css/icons/material/User.svg", "fields": [
                    { "name": "label", "label": "Bezeichnung", "type": "text" },
                    { "name": "password", "label": "Passwort", "type": "text" },
                    { "name": "isadmin", "label": "Administrator", "type": "boolean" },
                    { "name": "usergroupname", "label": "Benutzergruppe", "type": "reference", "reference": "usergroups" }
                ], "canhaverelations" : true }
                
            ]
        },

        "doc": {
            "forportal": true,
            "forclients": true,
            "api" : [ "doc" ],
            "doc" : [
                { "docCard": "Terms", "title" : "TRK_DOC_TERMS", "icon": "Dictionary", "index": 97 },
                { "docCard": "Concepts", "title" : "TRK_DOC_CONCEPTS", "icon": "Design", "index": 98 },
                { "docCard": "ReleaseNotes", "title" : "TRK_DOC_RELEASENOTES", "icon": "News", "index": 99 }
            ],
            "include" : [
                "public/js/Doc/ListController.js",
                "public/js/Doc/CardController.js"
            ],
            "languages" : [ "de", "en" ],
            "public" : [
                "css/icons/material/Design.svg",
                "css/icons/material/Dictionary.svg",
                "css/icons/material/News.svg",
                "css/images/Relations_add.png",
                "css/images/Relations_list.png",
                "css/images/Relations_menu.png",
                "css/images/Search_cancelbutton.png",
                "css/images/Search_searchbutton.png",
                "css/images/Search_searchfield.png",
                "css/images/Search_searchresults.png",
                "css/images/Search_toolbar.png",
                "css/images/Settings_dynamicattributes_values.png",
                "partial/Doc/Concepts.html",
                "partial/Doc/List.html",
                "partial/Doc/ReleaseNotes.html",
                "partial/Doc/Terms.html"
            ]
        },

        "activities": {
            "forportal": false,
            "forclients": true,
            "api" : [ "activities" ],
            "public" : [
                "css/icons/material/Planner.svg",
                "css/icons/office/Planner.svg",
                "css/images/Activities_add.png",
                "css/images/Activities_calendar.png",
                "css/images/Activities_new.png",
                "partial/Doc/Activities.html",
                "partial/Office/ActivityCard.html",
                "partial/Office/CalendarCard.html"
            ],
            "include" : [
                "public/js/Office/ActivityCardController.js",
                "public/js/Office/CalendarCardController.js"
            ],
            "languages" : [ "en", "de" ],
            "menu": [
                {
                    "title": "TRK_MENU_OFFICE",
                    "items": [
                        { "mainCard": "Office/CalendarCard", "icon": "/css/icons/material/Planner.svg", "title": "TRK_MENU_OFFICE_ACTIVITIES", "permission" : "PERMISSION_OFFICE_ACTIVITY", "docCard" : "Activities", "directurls": [ "activities" ] }
                    ]
                }
            ],
            "clientdatatypes": [

                { "name": "activitytypes", "label": "Terminart", "titlefield": "label", "fields": [
                    { "name": "label", "type": "text" }
                ], "values": [
                    { "name": "ACTIVITIES_TYPE_NONE", "label": "" },
                    { "name": "ACTIVITIES_TYPE_CALL_ON_CUSTOMERS", "label": "Kundenbesuch" },
                    { "name": "ACTIVITIES_TYPE_MAINTENANCE", "label": "Wartung" },
                    { "name": "ACTIVITIES_TYPE_WARRANTY", "label": "Gewährleistung" }
                ] }, 

                { "name": "activities", "label": "Termin", "plurallabel": "Termine", "titlefield": "label", "icon": "/css/icons/material/Planner.svg", "fields": [
                    { "name": "date", "label": "Datum", "type": "datetime" },
                    { "name": "label", "label": "Bezeichnung", "type": "text" },
                    { "name": "task", "label": "Aufgabe", "type": "text" },
                    { "name": "isdone", "label": "Erledigt", "type": "boolean" },
                    { "name": "activitytypename", "label": "Typ", "type": "reference", "reference": "activitytypes" },
                    { "name": "comment", "label": "Kommentar", "type": "text" },
                    { "name": "createdbyusername", "label": "Ersteller", "type": "reference", "reference": "users" },
                    { "name": "isforallusers", "label": "Sichtbar für alle Benutzer", "type": "boolean" }
                ], "canhaverelations" : true }

            ]
    
        },
        
        "areas": {
            "api" : [ "areas" ],
            "forportal": false,
            "forclients": true,
            "public" : [
                "css/icons/fm/FMOBJECTS_TYPE_AREA.svg",
                "css/icons/fm/FMOBJECTS_TYPE_BUILDING.svg",
                "css/icons/fm/FMOBJECTS_TYPE_INVENTORY.svg",
                "css/icons/fm/FMOBJECTS_TYPE_LEVEL.svg",
                "css/icons/fm/FMOBJECTS_TYPE_PROJECT.svg",
                "css/icons/fm/FMOBJECTS_TYPE_PROPERTY.svg",
                "css/icons/fm/FMOBJECTS_TYPE_ROOM.svg",
                "css/icons/material/surface.svg",
                "css/icons/office/surface.svg",
                "css/images/Areas_desktop.png",
                "css/images/Areas_mobile.png",
                "partial/Doc/Areas.html",
                "partial/BIM/AreasCard.html"
            ],
            "include" : [
                "public/js/BIM/AreasCardController.js"
            ],
            "languages" : [ "en", "de" ],
            "menu": [
                {
                    "title": "TRK_MENU_BIM",
                    "items": [
                        { "mainCard": "BIM/AreasCard", "icon": "/css/icons/material/surface.svg", "title": "TRK_MENU_BIM_AREAS", "permission" : "PERMISSION_BIM_AREAS", "docCard" : "Areas", "directurls": [ "area" ] }
                    ]
                }
            ]
        },

        "businesspartners" : {
            "forportal": false,
            "forclients": true,
            "api":[ "businesspartners", "partneraddresses", "persons", "communications"],
            "public": [
                "css/icons/material/Address Book.svg",
                "css/icons/material/Business.svg",
                "css/icons/material/Collaborator Male.svg",
                "css/icons/material/Email.svg",
                "css/icons/material/Phone.svg",
                "css/icons/material/Post Office.svg",
                "css/icons/material/Purchase Order.svg",
                "css/icons/material/Rating.svg",
                "css/icons/material/Truck.svg",
                "css/icons/office/Business.svg",               
                "css/icons/office/Collaborator Male.svg",
                "css/images/Businesspartners_add.png",
                "css/images/Businesspartners_addaddress.png",
                "css/images/Businesspartners_addresslist.png",
                "css/images/Businesspartners_edit.png",
                "css/images/Businesspartners_list.png",
                "css/images/Persons_add.png",
                "css/images/Persons_addcomm.png",
                "css/images/Persons_commlist.png",
                "css/images/Persons_edit.png",
                "css/images/Persons_list.png",
                "partial/CRM/BPAddressCard.html",
                "partial/CRM/BPCard.html",
                "partial/CRM/BPListCard.html",
                "partial/CRM/CommunicationCard.html",
                "partial/CRM/PersonCard.html",
                "partial/CRM/PersonListCard.html",
                "partial/Doc/BusinessPartners.html",
                "partial/Doc/Persons.html"
            ],
            "include":[
                "public/js/CRM/BPAddressCardController.js",
                "public/js/CRM/BPCardController.js",
                "public/js/CRM/BPListCardController.js",
                "public/js/CRM/CommunicationCardController.js",
                "public/js/CRM/PersonCardController.js",
                "public/js/CRM/PersonListCardController.js"
            ],
            "languages" : [ "en", "de" ],
            "menu": [
                {
                    "title": "TRK_MENU_CRM",
                    "items": [
                        { "mainCard": "CRM/BPListCard", "icon": "/css/icons/material/Business.svg", "title": "TRK_MENU_CRM_BUSINESSPARTNERS", "permission" : "PERMISSION_CRM_BUSINESSPARTNERS", "docCard" : "BusinessPartners", "directurls": [ "businesspartners" ] },
                        { "mainCard": "CRM/PersonListCard", "icon": "/css/icons/material/Collaborator Male.svg", "title": "TRK_MENU_CRM_PERSONS", "permission" : "PERMISSION_CRM_PERSONS", "docCard" : "Persons", "directurls": [ "persons" ] }
                    ]
                }
            ],

            "clientdatatypes": [

                { "name": "businesspartners", "label": "Geschäftspartner", "plurallabel": "Geschäftspartner", "titlefield": "label", "icon": "/css/icons/material/Business.svg", "fields": [
                    { "name": "label", "label": "Bezeichnung", "type": "text" },
                    { "name": "industry", "label": "Geschäftsbereich", "type": "text" },
                    { "name": "rolle", "label": "Art der Beziehung", "type": "text" },
                    { "name": "isjuristic", "label": "Juristische Person", "type": "boolean" }
                ], "canhaverelations" : true },

                { "name": "persons", "label": "Person", "plurallabel": "Personen", "titlefield": "lastname", "icon": "/css/icons/material/Collaborator Male.svg", "fields": [
                    { "name": "firstname", "label": "Vorname", "type": "text" },
                    { "name": "lastname", "label": "Nachname", "type": "text" },
                    { "name": "description", "label": "Beschreibung", "type": "text" }
                ], "canhaverelations" : true },

                { "name": "partneraddresstypes", "label": "Adressart", "titlefield": "label", "fields": [
                    { "name": "label", "type": "text" },
                    { "name": "icon", "type": "text" }
                ], "values": [
                    { "name": "Primaryaddress", "label": "Primäradresse", "icon": "/css/icons/material/Rating.svg" },
                    { "name": "Postaddress", "label": "Postadresse", "icon": "/css/icons/material/Post Office.svg" },
                    { "name": "Delivaryaddress", "label": "Lieferadresse", "icon": "/css/icons/material/Truck.svg" },
                    { "name": "Billaddress", "label": "Rechnungsadresse", "icon": "/css/icons/material/Purchase Order.svg" }
                ] }, 

                { "name": "partneraddresses", "label": "Adresse", "plurallabel": "Adressen", "titlefield": "addressee", "icon": "/css/icons/material/Address Book.svg", "fields": [
                    { "name": "addressee", "label": "Adressat", "type": "text" },
                    { "name": "businesspartnername", "label": "Geschäftspartner", "type": "reference", "reference": "businesspartners" },
                    { "name": "street", "label": "Straße und Hausnummer", "type": "text" },
                    { "name": "postcode", "label": "Postleitzahl", "type": "text" },
                    { "name": "city", "label": "Ort", "type": "text" },
                    { "name": "partneraddresstypename", "label": "Art der Adresse", "type": "reference", "reference": "partneraddresstypes" }
                ] },

                { "name": "communicationmediums", "label": "Kommunikationsmedium", "titlefield": "label", "fields": [
                    { "name": "label", "type": "text" }
                ], "values": [
                    { "name": "email", "label": "E-Mail" },
                    { "name": "phone", "label": "Telefon" }
                ] }, 

                { "name": "communicationtypes", "label": "Kommunikationsart", "titlefield": "label", "fields": [
                    { "name": "label", "type": "text" },
                    { "name": "communicationmediumname", "label": "Medium", "type": "reference", "reference": "communicationmediums" }
                ], "values": [
                    { "name": "emailwork", "label": "Arbeit", "communicationmediumname": "email" },
                    { "name": "emailother", "label": "Andere", "communicationmediumname": "email" },
                    { "name": "phonework", "label": "Arbeit", "communicationmediumname": "phone" },
                    { "name": "phonemobile", "label": "Mobil", "communicationmediumname": "phone" },
                    { "name": "phoneother", "label": "Andere", "communicationmediumname": "phone" }
                ] }, 

                { "name": "communications", "label": "Kommunikationsweg", "plurallabel": "Kommunikationswege", "titlefield": "contact", "icon": "/css/icons/material/Phone.svg", "fields": [
                    { "name": "contact", "label": "Kontakt", "type": "text" },
                    { "name": "personname", "label": "Person", "type": "reference", "reference": "persons" },
                    { "name": "communicationtypename", "label": "Typ", "type": "reference", "reference": "communicationtypes" }
                ], "canhaverelations" : true }
                
            ]
        },

        "clients": {
            "forportal": true,
            "forclients": false,
            "api" : [ "clients", "clientmodules" ],
            "public" : [
                "css/icons/material/Add User Male.svg",
                "css/icons/material/Briefcase.svg",
                "css/icons/material/Module.svg",
                "css/icons/office/Add User Male.svg",
                "css/icons/office/Briefcase.svg",
                "css/icons/office/Module.svg",
                "css/images/Clients_add_button.png",
                "css/images/Clients_createadmin.png",
                "css/images/Clients_createclient.png",
                "css/images/Clients_editclient.png",
                "css/images/Clients_list.png",
                "css/images/Clients_modules.png",
                "partial/Administration/ClientCard.html",
                "partial/Administration/ClientListCard.html",
                "partial/Doc/Clients.html"
            ],
            "include" : [
                "public/js/Administration/ClientCardController.js",
                "public/js/Administration/ClientListCardController.js"
            ],
            "languages" : [ "en", "de" ],
            "menu": [
                {
                    "title": "TRK_MENU_PORTAL",
                    "items": [
                        { "mainCard": "Administration/ClientListCard", "icon": "/css/icons/material/Briefcase.svg", "title": "TRK_MENU_PORTAL_CLIENTS", "permission" : "PERMISSION_ADMINISTRATION_CLIENT", "docCard" : "Clients", "directurls": [ "clients" ] }
                    ]
                }
            ],
            "portaldatatypes": [

                { "name": "clients", "label": "Mandant", "plurallabel": "Mandanten", "titlefield": "label", "icon": "/css/icons/material/Briefcase.svg", "fields": [
                    { "name": "label", "label": "Bezeichnung", "type": "text" }
                ], "canhaverelations" : true }
                
            ]
        },

        "documents": {
            "forportal": false,
            "forclients": true,
            "api" : [ "documents", "extractdocument", "folders" ],
            "public" : [
                "css/icons/material/Add Folder.svg",
                "css/icons/material/Document.svg",
                "css/icons/material/Download.svg",
                "css/icons/material/Folder.svg",
                "css/icons/material/Upload.svg",
                "css/icons/office/Add Folder.svg",
                "css/icons/office/Document.svg",
                "css/icons/office/Download.svg",
                "css/icons/office/Folder.svg",
                "css/icons/office/Upload.svg",
                "css/images/Documents_addfolder.png",
                "css/images/Documents_editdocument.png",
                "css/images/Documents_editfolder.png",
                "css/images/Documents_hierarchy.png",
                "css/images/Documents_upload.png",
                "css/images/Documents_uploadmobile.png",
                "partial/Doc/Documents.html",
                "partial/Office/DocumentCard.html",
                "partial/Office/DocumentListCard.html",
                "partial/Office/FolderCard.html"
            ],
            "include" : [
                "public/js/Office/DocumentCardController.js",
                "public/js/Office/DocumentListCardController.js",
                "public/js/Office/FolderCardController.js"
            ],
            "languages" : [ "en", "de" ],
            "utils": [ "documentsHelper" ],
            "menu": [
                {
                    "title": "TRK_MENU_OFFICE",
                    "items": [
                        { "mainCard": "Office/DocumentListCard", "icon": "/css/icons/material/Document.svg", "title": "TRK_MENU_OFFICE_DOCUMENTS", "permission" : "PERMISSION_OFFICE_DOCUMENT", "docCard" : "Documents", "directurls": [ "documents", "folders" ] }
                    ]
                }
            ],
            "clientdatatypes": [

                { "name": "folders", "label": "Verzeichnis", "plurallabel": "Verzeichnisse", "titlefield": "label", "icon": "/css/icons/material/Folder.svg", "fields": [
                    { "name": "label", "label": "Bezeichnung", "type": "text" },
                    { "name": "parentfoldername", "type": "reference", "reference": "folders" }
                ], "lists": [ "folders" ], "canhaverelations" : true },

                { "name": "documents", "label": "Dokument", "plurallabel": "Dokumente", "titlefield": "label", "icon": "/css/icons/material/Document.svg", "fields": [
                    { "name": "label", "label": "Bezeichnung", "type": "text" },
                    { "name": "parentfoldername", "type": "reference", "reference": "folders" },
                    { "name": "type", "type": "text" },
                    { "name": "isshared", "label": "Öffentlich zugänglich", "type": "boolean" }
                ], "lists": [ "folders" ], "canhaverelations" : true }

            ]
        },

        "fmobjects": {
            "forportal": false,
            "forclients": true,
            "public" : [
                "css/icons/material/Cottage.svg",
                "css/icons/material/Sort Down.svg",
                "css/icons/material/Sort Right.svg",
                "css/icons/office/Cottage.svg",
                "css/icons/office/Sort Down.svg",
                "css/icons/office/Sort Right.svg",
                "css/icons/fm/FMOBJECTS_TYPE_AREA.svg",
                "css/icons/fm/FMOBJECTS_TYPE_BUILDING.svg",
                "css/icons/fm/FMOBJECTS_TYPE_INVENTORY.svg",
                "css/icons/fm/FMOBJECTS_TYPE_LEVEL.svg",
                "css/icons/fm/FMOBJECTS_TYPE_PROJECT.svg",
                "css/icons/fm/FMOBJECTS_TYPE_PROPERTY.svg",
                "css/icons/fm/FMOBJECTS_TYPE_ROOM.svg",
                "css/images/FM_add.png",
                "css/images/FM_addsub.png",
                "css/images/FM_edit.png",
                "css/images/FM_hierarchy.png",
                "partial/components/DetailsCard.html",
                "partial/components/HierarchyCard.html",
                "partial/Doc/FmObjects.html"
            ],
            "languages" : [ "en", "de" ],
            "menu": [
                {
                    "title": "TRK_MENU_BIM",
                    "items": [
                        { "mainCard": "components/HierarchyCard", "icon": "/css/icons/material/Cottage.svg", "title": "TRK_MENU_BIM_FMOBJECTS", "permission" : "PERMISSION_BIM_FMOBJECT", "docCard" : "FmObjects", "listfilter": "fmobjects", "directurls": [ "fmobjects", "inventories", "areas", "rooms", "levels", "buildings", "properties", "projects" ] }
                    ]
                }
            ],
            "clientdatatypes": [

                { "name": "projects", "label": "Projekt", "plurallabel": "Projekte", "titlefield": "label", "icon": "css/icons/fm/FMOBJECTS_TYPE_PROJECT.svg", "fields": [
                    { "name": "label", "label": "Bezeichnung", "type": "text" },
                    { "name": "previewimagedocumentname", "label": "Foto", "type": "reference", "reference": "documents", "isnullable": "true" },
                    { "name": "bgf", "label": "Brutto-Grundfläche (BGF)", "type": "formula", "formula": { "childsum" : "bgf" }, "formulaindex": 0 },
                    { "name": "nrf", "label": "Netto-Raumfläche (NRF)", "type": "formula", "formula": { "childsum" : "nrf" }, "formulaindex": 1 },
                    { "name": "kgf", "label": "Konstruktions-Grundfläche (KGF)", "type": "formula", "formula": { "childsum" : "kgf" }, "formulaindex": 2 },
                    { "name": "nuf", "label": "Nutzungsfläche (NUF)", "type": "formula", "formula": { "childsum" : "nuf" }, "formulaindex": 3 },
                    { "name": "tf", "label": "Technische Funktionsfläche (TF)", "type": "formula", "formula": { "childsum" : "tf" }, "formulaindex": 4 },
                    { "name": "vf", "label": "Verkehrsfläche (VF)", "type": "formula", "formula": { "childsum" : "vf" }, "formulaindex": 5 }
                ], "lists": [ "fmobjects", "areas" ], "permissionkey": "PERMISSION_BIM_FMOBJECT", "canhaverelations" : true },

                { "name": "properties", "label": "Liegenschaft", "plurallabel": "Liegenschaften", "titlefield": "label", "icon": "css/icons/fm/FMOBJECTS_TYPE_PROPERTY.svg", "fields": [
                    { "name": "label", "label": "Bezeichnung", "type": "text" },
                    { "name": "previewimagedocumentname", "label": "Foto", "type": "reference", "reference": "documents", "isnullable": "true" },
                    { "name": "bgf", "label": "Brutto-Grundfläche (BGF)", "type": "formula", "formula": { "childsum" : "bgf" }, "formulaindex": 0 },
                    { "name": "nrf", "label": "Netto-Raumfläche (NRF)", "type": "formula", "formula": { "childsum" : "nrf" }, "formulaindex": 1 },
                    { "name": "kgf", "label": "Konstruktions-Grundfläche (KGF)", "type": "formula", "formula": { "childsum" : "kgf" }, "formulaindex": 2 },
                    { "name": "nuf", "label": "Nutzungsfläche (NUF)", "type": "formula", "formula": { "childsum" : "nuf" }, "formulaindex": 3 },
                    { "name": "tf", "label": "Technische Funktionsfläche (TF)", "type": "formula", "formula": { "childsum" : "tf" }, "formulaindex": 4 },
                    { "name": "vf", "label": "Verkehrsfläche (VF)", "type": "formula", "formula": { "childsum" : "vf" }, "formulaindex": 5 }
                ], "lists": [ "fmobjects", "areas" ], "permissionkey": "PERMISSION_BIM_FMOBJECT", "canhaverelations" : true },

                { "name": "buildings", "label": "Gebäude", "plurallabel": "Gebäude", "titlefield": "label", "icon": "css/icons/fm/FMOBJECTS_TYPE_BUILDING.svg", "fields": [
                    { "name": "label", "label": "Bezeichnung", "type": "text" },
                    { "name": "previewimagedocumentname", "label": "Foto", "type": "reference", "reference": "documents", "isnullable": "true" },
                    { "name": "bgf", "label": "Brutto-Grundfläche (BGF)", "type": "formula", "formula": { "childsum" : "bgf" }, "formulaindex": 0 },
                    { "name": "nrf", "label": "Netto-Raumfläche (NRF)", "type": "formula", "formula": { "childsum" : "nrf" }, "formulaindex": 1 },
                    { "name": "kgf", "label": "Konstruktions-Grundfläche (KGF)", "type": "formula", "formula": { "childsum" : "kgf" }, "formulaindex": 2 },
                    { "name": "nuf", "label": "Nutzungsfläche (NUF)", "type": "formula", "formula": { "childsum" : "nuf" }, "formulaindex": 3 },
                    { "name": "tf", "label": "Technische Funktionsfläche (TF)", "type": "formula", "formula": { "childsum" : "tf" }, "formulaindex": 4 },
                    { "name": "vf", "label": "Verkehrsfläche (VF)", "type": "formula", "formula": { "childsum" : "vf" }, "formulaindex": 5 }
                ], "lists": [ "fmobjects", "areas" ], "permissionkey": "PERMISSION_BIM_FMOBJECT", "canhaverelations" : true },

                { "name": "levels", "label": "Etage", "plurallabel": "Etagen", "titlefield": "label", "icon": "css/icons/fm/FMOBJECTS_TYPE_LEVEL.svg", "fields": [
                    { "name": "label", "label": "Bezeichnung", "type": "text" },
                    { "name": "previewimagedocumentname", "label": "Foto", "type": "reference", "reference": "documents", "isnullable": "true" },
                    { "name": "bgf", "label": "Brutto-Grundfläche (BGF)", "type": "formula", "formula": { "childsum" : "bgf" }, "formulaindex": 0 },
                    { "name": "nrf", "label": "Netto-Raumfläche (NRF)", "type": "formula", "formula": { "childsum" : "nrf" }, "formulaindex": 1 },
                    { "name": "nuf", "label": "Nutzungsfläche (NUF)", "type": "formula", "formula": { "childsum" : "nuf" }, "formulaindex": 2 },
                    { "name": "tf", "label": "Technische Funktionsfläche (TF)", "type": "formula", "formula": { "childsum" : "tf" }, "formulaindex": 3 },
                    { "name": "vf", "label": "Verkehrsfläche (VF)", "type": "formula", "formula": { "childsum" : "vf" }, "formulaindex": 4 },
                    { "name": "kgf", "label": "Konstruktions-Grundfläche (KGF)", "type": "formula", "formula": { "sum" : ["bgf", "-nrf"] }, "formulaindex": 5 }
                ], "lists": [ "fmobjects", "areas" ], "permissionkey": "PERMISSION_BIM_FMOBJECT", "canhaverelations" : true },

                { "name": "rooms", "label": "Raum", "plurallabel": "Räume", "titlefield": "label", "icon": "css/icons/fm/FMOBJECTS_TYPE_ROOM.svg", "fields": [
                    { "name": "label", "label": "Bezeichnung", "type": "text" },
                    { "name": "previewimagedocumentname", "label": "Foto", "type": "reference", "reference": "documents", "isnullable": "true" },
                    { "name": "nuf", "label": "Nutzungsfläche (NUF)", "type": "formula", "formula": { "childsum" : "nuf" }, "formulaindex": 0 },
                    { "name": "tf", "label": "Technische Funktionsfläche (TF)", "type": "formula", "formula": { "childsum" : "tf" }, "formulaindex": 1 },
                    { "name": "vf", "label": "Verkehrsfläche (VF)", "type": "formula", "formula": { "childsum" : "vf" }, "formulaindex": 2 },
                    { "name": "nrf", "label": "Netto-Raumfläche (NRF, berechnet)", "type": "formula", "formula": { "sum" : ["nuf", "tf", "vf"] }, "formulaindex": 3 }
                ], "lists": [ "fmobjects", "areas" ], "permissionkey": "PERMISSION_BIM_FMOBJECT", "canhaverelations" : true },

                { "name": "areas", "label": "Fläche", "plurallabel": "Flächen", "titlefield": "label", "icon": "css/icons/fm/FMOBJECTS_TYPE_AREA.svg", "fields": [
                    { "name": "label", "label": "Bezeichnung", "type": "text" },
                    { "name": "previewimagedocumentname", "label": "Foto", "type": "reference", "reference": "documents", "isnullable": "true" },
                    { "name": "areacategoryname", "label": "Kategorie", "type": "reference", "reference": "areacategories" },
                    { "name": "areatypename", "label": "Flächenart", "type": "reference", "reference": "areatypes" },
                    { "name": "areausagestatename", "label": "Nutzungsstatus", "type": "reference", "reference": "areausagestates" },
                    { "name": "f", "label": "Flächeninhalt (m²)", "type": "decimal" },
                    { "name": "nuf", "label": "Nutzungsfläche (NUF)", "type": "formula", "formula": { "ifthenelse" : ["areacategoryname", "FMOBJECTS_CATEGORY_NUF", "f", null] }, "formulaindex": 0 },
                    { "name": "tf", "label": "Technische Funktionsfläche (TF)", "type": "formula", "formula": { "ifthenelse" : ["areacategoryname", "FMOBJECTS_CATEGORY_TF", "f", null] }, "formulaindex": 1 },
                    { "name": "vf", "label": "Verkehrsfläche (VF)", "type": "formula", "formula": { "ifthenelse" : ["areacategoryname", "FMOBJECTS_CATEGORY_VF", "f", null] }, "formulaindex": 2 }
                ], "lists": [ "fmobjects", "areas" ], "permissionkey": "PERMISSION_BIM_FMOBJECT", "canhaverelations" : true },

                { "name": "inventories", "label": "Inventar", "plurallabel": "Inventare", "titlefield": "label", "icon": "css/icons/fm/FMOBJECTS_TYPE_INVENTORY.svg", "fields": [
                    { "name": "label", "label": "Bezeichnung", "type": "text" },
                    { "name": "previewimagedocumentname", "label": "Foto", "type": "reference", "reference": "documents", "isnullable": "true" }
                ], "lists": [ "fmobjects" ], "permissionkey": "PERMISSION_BIM_FMOBJECT", "canhaverelations" : true },

                { "name": "fmobjecttypes", "label": "FM Objekttyp", "titlefield": "label", "fields": [
                    { "name": "label", "type": "text" }
                ], "values": [
                    { "name": "FMOBJECTS_TYPE_PROJECT", "label": "Projekt" },
                    { "name": "FMOBJECTS_TYPE_PROPERTY", "label": "Liegenschaft" },
                    { "name": "FMOBJECTS_TYPE_BUILDING", "label": "Gebäude" },
                    { "name": "FMOBJECTS_TYPE_LEVEL", "label": "Etage" },
                    { "name": "FMOBJECTS_TYPE_ROOM", "label": "Raum" },
                    { "name": "FMOBJECTS_TYPE_AREA", "label": "Fläche" },
                    { "name": "FMOBJECTS_TYPE_INVENTORY", "label": "Inventar" }
                ] }, 

                { "name": "areacategories", "label": "Kategorie", "titlefield": "label", "fields": [
                    { "name": "label", "type": "text" }
                ], "values": [
                    { "name": "FMOBJECTS_CATEGORY_NUF", "label": "Nutzungsfläche" },
                    { "name": "FMOBJECTS_CATEGORY_TF", "label": "Technikfläche" },
                    { "name": "FMOBJECTS_CATEGORY_VF", "label": "Verkehrsfläche" }
                ] }, 

                { "name": "areatypes", "label": "Flächenart", "titlefield": "name", "fields": [
                    { "name": "areacategoryname", "type": "reference", "reference": "areacategories" }
                ], "values": [
                    { "name": "Wohnen und Aufenthalt", "areacategoryname": "Nutzungsfläche" },
                    { "name": "Büroarbeit", "areacategoryname": "Nutzungsfläche" },
                    { "name": "Produktion, Hand- und Maschinenarbeit, Experimente", "areacategoryname": "Nutzungsfläche" },
                    { "name": "Lagern, Verteilen und Verkaufen", "areacategoryname": "Nutzungsfläche" },
                    { "name": "Bildung, Unterricht und Kultur", "areacategoryname": "Nutzungsfläche" },
                    { "name": "Heilen und Pflegen", "areacategoryname": "Nutzungsfläche" },
                    { "name": "Sonstige Nutzung", "areacategoryname": "Nutzungsfläche" },
                    { "name": "Technische Anlagen", "areacategoryname": "Technikfläche" },
                    { "name": "Verkehrserschließung und -sicherung", "areacategoryname": "Verkehrsfläche" }
                ] }, 

                { "name": "areausagestates", "label": "Nutzungsstatus", "titlefield": "name", "values": [
                    { "name": "Ungenutzt" },
                    { "name": "Eigengenutzt" },
                    { "name": "Vermietet" },
                    { "name": "Reserviert" }
                ] }, 

                { "name": "fmobjects", "label": "FM Objekt", "plurallabel": "FM Objekte", "titlefield": "label", "icon": "/css/icons/material/Cottage.svg", "fields": [
                    { "name": "label", "label": "Bezeichnung", "type": "text" },
                    { "name": "fmobjecttypename", "label": "Typ", "type": "reference", "reference": "fmobjecttypes" },
                    { "name": "parentfmobjectname", "type": "reference", "reference": "fmobjects" },
                    { "name": "previewimagedocumentname", "label": "Bild", "type": "reference", "reference": "documents", "isnullable": "true" },
                    { "name": "areatypename", "label": "Flächenart", "type": "reference", "reference": "areatypes" },
                    { "name": "f", "label": "Fläche (m²)", "type": "decimal" },
                    { "name": "bgf", "label": "Brutto-Geschoss-Fläche (BGF)", "type": "decimal" },
                    { "name": "areausagestatename", "label": "Nutzungsstatus", "type": "reference", "reference": "areausagestates" },
                    { "name": "nrf", "label": "Netto-Raum-Fläche (NRF)", "type": "decimal" },
                    { "name": "nuf", "label": "Nutzungsfläche (NUF)", "type": "decimal" },
                    { "name": "tf", "label": "Technikfläche (TF)", "type": "decimal" },
                    { "name": "vf", "label": "Verkehrsfläche (VF)", "type": "decimal" }
                ] }

            ]
        },

        "licenseserver" : {
            "forportal": true,
            "forclients": false,
            "api" : [ "portalmodules", "portals", "triggerUpdate", "update" ],
            "public" : [
                "css/icons/material/Checkmark.svg",
                "css/icons/material/Module.svg",
                "css/icons/material/Server.svg",
                "css/icons/material/Unavailable.svg",
                "css/icons/office/Module.svg",
                "css/icons/office/Server.svg",
                "css/images/Portals_add.png",
                "css/images/Portals_edit.png",
                "css/images/Portals_list.png",
                "css/images/Portals_modules.png",
                "partial/Doc/Portals.html",
                "partial/LicenseServer/PortalCard.html",
                "partial/LicenseServer/PortalListCard.html"
            ],
            "include" : [
                "public/js/LicenseServer/PortalCardController.js",
                "public/js/LicenseServer/PortalListCardController.js"
            ],
            "languages" : [ "en", "de" ],
            "menu" : [
                {
                    "title": "TRK_MENU_LICENSESERVER",
                    "items": [
                        { "mainCard": "LicenseServer/PortalListCard", "icon": "/css/icons/material/Server.svg", "title": "TRK_MENU_LICENSESERVER_PORTALS", "permission" : "PERMISSION_LICENSESERVER_PORTAL", "docCard" : "Portals", "directurls": [ "portals" ] }
                    ]
                }
            ],
            "utils": [ "app-packager" ],
            "portaldatatypes": [

                { "name": "portals", "label": "Portal", "plurallabel": "Portale", "titlefield": "label", "icon": "/css/icons/material/Server.svg", "fields": [
                    { "name": "label", "label": "Bezeichnung", "type": "text" },
                    { "name": "isactive", "label": "Aktiv", "type": "boolean" },
                    { "name": "url", "label": "URL", "type": "text" },
                    { "name": "comment", "label": "Kommentar", "type": "text" },
                    { "name": "licensekey", "label": "Lizenzschlüssel", "type": "text" },
                    { "name": "version", "label": "Version", "type": "text" },
                    { "name": "lastnotification", "label": "Letzte Meldung", "type": "datetime" }
                ], "canhaverelations" : true },

                { "name": "portalmodules", "label": "Portalmodul", "plurallabel": "Portalmodule", "fields": [
                    { "name": "portalname", "type": "reference", "reference": "portals" },
                    { "name": "modulename", "label": "Modul", "type": "text" }
                ] }
                
            ]
        },

        "notes": {
            "forportal": false,
            "forclients": true,
            "api" : [ "notes" ],
            "public" : [
                "css/icons/material/Notes.svg",                
                "css/images/Notes_add_button.png",
                "css/images/Notes_editnote.png",
                "css/images/Notes_list.png",
                "css/icons/office/Notes.svg",
                "partial/Office/NoteCard.html",
                "partial/Office/NoteListCard.html",
                "partial/Doc/Notes.html"
            ],
            "include" : [
                "public/js/Office/NoteCardController.js",
                "public/js/Office/NoteListCardController.js"
            ],
            "languages" : [ "en", "de" ],
            "menu": [
                {
                    "title": "TRK_MENU_OFFICE",
                    "items": [
                        { "mainCard": "Office/NoteListCard", "icon": "/css/icons/material/Notes.svg", "title": "TRK_MENU_OFFICE_NOTES", "permission" : "PERMISSION_OFFICE_NOTE", "docCard" : "Notes", "directurls": [ "notes" ] }
                    ]
                }
            ],
            "clientdatatypes": [

                { "name": "notes", "label": "Notiz", "plurallabel": "Notizen", "titlefield": "content", "icon": "/css/icons/material/Notes.svg", "fields": [
                    { "name": "content", "label": "Inhalt", "type": "text" }
                ], "canhaverelations" : true }

            ]
        },

        "portalbase" : {
            "forportal": true,
            "forclients": false,
            "api" : [ "portalmanagement" ],
            "public" : [
                "css/icons/material/Settings.svg",
                "css/icons/office/Settings.svg",
                "partial/Administration/PortalSettingsCard.html"
            ],
            "include" : [
                "public/js/Administration/PortalSettingsCardController.js"
            ],
            "languages" : [ "en", "de" ],
            "settingsets" : [
                { "mainCard": "Administration/PortalSettingsCard", "title": "TRK_SETTINGSET_PORTAL_GENERAL", "type": "SETTINGSET_TYPE_PORTAL", "icon": "Server", "permission": "PERMISSION_SETTINGS_PORTAL" }
            ],
            "utils" :["portalUpdatesHelper"]
        },

        "recordtypes": {
            "forportal": true,
            "forclients": true,
            "api" : [ "recordtypes" ],
            "public" : [
                "css/icons/material/icons8-categorize.svg",
                "css/icons/office/icons8-categorize.svg",
                "partial/Administration/RecordTypeDetailsCard.html",
                "partial/Administration/RecordTypeListCard.html"
            ],
            "include" : [
                "public/js/Administration/RecordTypeDetailsCardController.js",
                "public/js/Administration/RecordTypeListCardController.js"
            ],
            "languages" : [ "en", "de" ],
            "settingsets" : [
                { "mainCard": "Administration/RecordTypeListCard", "title": "TRK_SETTINGSET_RECORDTYPES", "type": "SETTINGSET_TYPE_CLIENT", "icon": "icons8-categorize", "permission": "PERMISSION_SETTINGS_CLIENT_RECORDTYPES"}
            ]
        },

        "ronnyseins" : {
            "forportal": false,
            "forclients": true,
            "api" : [ "markers" ],
            "public" : [
                "css/icons/userlocation.png",
                "css/icons/material/Collapse.svg",
                "css/icons/material/Expand.svg",
                "css/icons/material/Virtual Reality.svg",
                "css/icons/office/Virtual Reality.svg",
                "css/icons/material/World Map.svg",
                "css/icons/office/World Map.svg",
                "partial/ronnyseins/3DCard.html",
                "partial/ronnyseins/AugmentedRealityCard.html",
                "partial/ronnyseins/GoogleMapsCard.html"
            ],
            "include" : [
                "public/js/lib/babylon.js",
                "public/js/lib/aframe-v0.7.0.min.js",
                "public/js/lib/aframe-look-at-billboard-component.min.js",
                "public/js/ronnyseins/3DCardController.js",
                "public/js/ronnyseins/AugmentedRealityCardController.js",
                "public/js/ronnyseins/GoogleMapsCardController.js"
            ],
            "menu" : [
                {
                    "title": "TRK_MENU_LAB",
                    "items": [
                        { "mainCard": "ronnyseins/AugmentedRealityCard", "icon": "/css/icons/material/Virtual Reality.svg", "title": "TRK_MENU_LAB_AUGMENTEDREALITY" },
                        { "mainCard": "ronnyseins/GoogleMapsCard", "icon": "/css/icons/material/World Map.svg", "title": "TRK_MENU_LAB_GOOGLEMAPS" }
                    ]
                }
            ],
            "clientdatatypes": [

                { "name": "markers", "label": "Markierung", "plurallabel": "Markierungen", "titlefield": "label", "fields": [
                    { "name": "label", "label": "Bezeichnung", "type": "text" },
                    { "name": "lat", "label": "Breitengrad (LAT)", "type": "text" },
                    { "name": "lon", "label": "Längengrad (LON)", "type": "text" }
                ] }

            ]
        }
        
    }
}